lighthouse/__init__.py
lighthouse_dev-0.0.1.dev0.dist-info/LICENSE
lighthouse_dev-0.0.1.dev0.dist-info/METADATA
lighthouse_dev-0.0.1.dev0.dist-info/WHEEL
lighthouse_dev-0.0.1.dev0.dist-info/top_level.txt
lighthouse_dev-0.0.1.dev0.dist-info/RECORD
