Metadata-Version: 2.1
Name: lighthouse-dev
Version: 0.0.1.dev0
Summary: Data observability made easy.
Author: Mihir Trivedi
Author-email: mtrivedi50@gmail.com
License: Apache-2.0
Platform: unix
Platform: linux
Platform: osx
Platform: win32
Classifier: Programming Language :: Python :: 3.12
Requires-Python: >=3.11
License-File: LICENSE
Requires-Dist: pydantic==2.10.2
Requires-Dist: sqlmodel==0.0.22
Requires-Dist: pydantic-settings==2.6.1
Requires-Dist: pydantic_core==2.27.1
Requires-Dist: rich==13.9.4
Requires-Dist: SQLAlchemy==2.0.36
Provides-Extra: dev
Requires-Dist: mypy>=1.11; extra == "dev"
Requires-Dist: pytest>=7; extra == "dev"
Requires-Dist: mkdocs==1.6.1; extra == "dev"
Requires-Dist: mkdocs-material==9.5.39; extra == "dev"
Requires-Dist: sqlalchemy2-stubs==0.0.2a38; extra == "dev"
Requires-Dist: pre-commit==3.8.0; extra == "dev"
Requires-Dist: twine==5.1.1; extra == "dev"
Requires-Dist: build==1.2.2.post1; extra == "dev"
